Metadata-Version: 1.1
Name: pyspeechwin3
Version: 0.0.2
Summary: Text To Speech Converter
Home-page: UNKNOWN
Author: Sunami Dasgupta
Author-email: sunamidasgupta@gmail.com
License: MIT
Keywords: Text to Speech,pyttsx3,tts for python,text to speech for python,offline text to speech for python
Platform: UNKNOWN
Classifier: Development Status :: 5 - Production/Stable
Classifier: Intended Audience :: Education
Classifier: Operating System :: Microsoft :: Windows :: Windows 10
Classifier: License :: OSI Approved :: MIT License
Classifier: Programming Language :: Python :: 3
